README.md
setup.py
Nebula/Abyss.py
Nebula/Ion.py
Nebula/Nebula.py
Nebula/NebulaCore.py
Nebula/NebulaObject.py
Nebula/__init__.py
Nebula/_autoCFG.py
Nebula/_setup.py
Nebula_Beta.egg-info/PKG-INFO
Nebula_Beta.egg-info/SOURCES.txt
Nebula_Beta.egg-info/dependency_links.txt
Nebula_Beta.egg-info/requires.txt
Nebula_Beta.egg-info/top_level.txt