Metadata-Version: 2.1
Name: Nebula-Beta
Version: 0.1.4
Summary: An Engine/Framework For Crafting 2d Games With Python+Pygame-Ce.
Home-page: https://github.com/setoyuma/NebulaEngine
Author: Setoichi
Author-email: setoichi.dev@gmail.com
License: MIT
Classifier: Development Status :: 4 - Beta
